cpu.v
module cpu (
    input wire clk,         // Clock signal
    input wire reset,       // Reset signal
    output wire [3:0] acc   // Output the value of accumulator register
);

    reg [3:0] PC;           // Program Counter
    reg [7:0] IR;           // Instruction Register (8-bit wide)
    reg [3:0] R0, R1;       // General purpose registers
    reg [3:0] ACC;          // Accumulator
    reg [3:0] memory [0:15];// Simple 4-bit memory for instructions
    reg [3:0] data_memory [0:15]; // Data memory
    reg [3:0] alu_out;      // Output of ALU
    reg [3:0] opcode, operand;
    reg [1:0] state;        // State variable for FSM

    // States for instruction cycle
    parameter FETCH = 2'b00, DECODE = 2'b01, EXECUTE = 2'b10;

    // ALU Logic
    always @(*) begin
        case(opcode)
            4'b0010: alu_out = R0 + R1;  // ADD
            4'b0011: alu_out = R0 - R1;  // SUB
            4'b0100: alu_out = R0 & R1;  // AND
            4'b0101: alu_out = R0 | R1;  // OR
            4'b0111: alu_out = ~(R0 ^ R1); //XNOR
            default: alu_out = 4'b0000;  // Default NOP
        endcase
    end

    // Control Unit FSM
    always @(posedge clk or posedge reset) begin
        if (reset) begin
            PC <= 4'b0000;
            ACC <= 4'b0000;
            IR <= 8'b00000000;
            state <= FETCH;
        end else begin
            case (state)
                FETCH: begin
                    
                    IR <= {memory[PC + 1], memory[PC]};  // Fetch instruction
                    PC <= PC + 2;                        // Increment PC by 2
                    state <= DECODE;
                end
                DECODE: begin
                    opcode <= IR[3:0];      // Decode the opcode
                    operand <= IR[7:4];     // Decode the operand
                    state <= EXECUTE;
                end
                EXECUTE: begin
                    case (opcode)
                        4'b0000: state <= FETCH;  // NOP: go back to fetch
                        4'b0001: begin            // LOAD constant to ACC
                            ACC <= operand;
                            state <= FETCH;
                        end
                        4'b0010, 4'b0011, 4'b0100, 4'b0101, 4'b0111: begin  // ALU operations
                            R0 <= data_memory[0];
                            R1 <= data_memory[1];  // Assume second register holds data for now
                            @(posedge clk) begin ACC <= alu_out;
                            end
                            state <= FETCH;

                        end
                        4'b0110: begin            // STORE ACC to memory
                            data_memory[operand] <= ACC;
                            state <= FETCH;
                        end
                        4'b0111: begin            // JMP to address
                            PC <= operand;
                            state <= FETCH;
                        end
                        default: state <= FETCH;  // Unknown opcode
                    endcase
                end
            endcase
        end
    end

    assign acc = ACC;  // Output the current value of ACC

endmodule

cpu_tb.v
`timescale 1ns/1ps

module tb_cpu;
    // Signal declarations
    reg clk;                  // Clock signal
    reg reset;                // Reset signal
    wire [3:0] acc;           // Accumulator output from CPU module

    // Instantiate the CPU module under test (UUT)
    cpu uut (
        .clk(clk),
        .reset(reset),
        .acc(acc)
    );

    // Clock generation: 10 ns period (50 MHz)
    initial begin
        clk = 0;
        forever #5 clk = ~clk;
    end

    // Test sequence
    initial begin
        // Enable GTKWave dump file generation
        $dumpfile("cpu_test.vcd");   // Specify the .vcd file name
        $dumpvars(0, tb_cpu);        // Record all variables in the tb_cpu module

        // Enhanced Monitor Statement for Readability
        $monitor("Time = %0dns | PC = %h | ACC (Accumulator) = %h | IR (Instruction) = %h | Operand = %b | Opcode = %b | R0 = %b | R1 = %b | ALU Output = %b",
                 $time, uut.PC, acc, uut.IR, uut.operand, uut.opcode, uut.R0, uut.R1, uut.alu_out);

        // Initialize the reset signal
        reset = 1;                     // Activate reset
        #10;
        reset = 0;                     // Release reset

        // Memory Initialization
        // Data memory: Storing immediate data values
        uut.data_memory[0] = 4'b0100;  // Example data
        uut.data_memory[1] = 4'b0010;  // Example data

        // Instruction memory: Loading a series of instructions
        // Format: [Opcode, Operand]
        uut.memory[0] = 4'b0001;  // LOADucti instron (Opcode for LOAD)
        uut.memory[1] = 4'b0011;  // Operand value: 3

        uut.memory[2] = 4'b0010;  // ADD instruction (Opcode for ADD)
        uut.memory[3] = 4'b0000;  // Operand value: 0

        uut.memory[4] = 4'b0101;  // ADD instruction
        uut.memory[5] = 4'b0000;  // Operand value: 0

        uut.memory[6] = 4'b0011;  // ADD instruction
        uut.memory[7] = 4'b0000;  // Operand value: 0

        uut.memory[8] = 4'b0100;  // ADD instruction
        uut.memory[9] = 4'b0000;  // Operand value: 0

        uut.memory[10] = 4'b0111; // ADD instruction
        uut.memory[11] = 4'b0000; // Operand value: 0

        // Run the simulation for a sufficient time to observe instruction execution
        #400;

        // End simulation
        $finish;
    end
endmodule

cpu_test.vcd
$date
	Tue Nov 12 21:19:23 2024
$end
$version
	Icarus Verilog
$end
$timescale
	1ps
$end
$scope module tb_cpu $end
$var wire 4 ! acc [3:0] $end
$var reg 1 " clk $end
$var reg 1 # reset $end
$scope module uut $end
$var wire 4 $ acc [3:0] $end
$var wire 1 " clk $end
$var wire 1 # reset $end
$var parameter 2 % DECODE $end
$var parameter 2 & EXECUTE $end
$var parameter 2 ' FETCH $end
$var reg 4 ( ACC [3:0] $end
$var reg 8 ) IR [7:0] $end
$var reg 4 * PC [3:0] $end
$var reg 4 + R0 [3:0] $end
$var reg 4 , R1 [3:0] $end
$var reg 4 - alu_out [3:0] $end
$var reg 4 . opcode [3:0] $end
$var reg 4 / operand [3:0] $end
$var reg 2 0 state [1:0] $end
$upscope $end
$upscope $end
$enddefinitions $end
$comment Show the parameter values. $end
$dumpall
b0 '
b10 &
b1 %
$end
#0
$dumpvars
b0 0
bx /
bx .
bx -
bx ,
bx +
b0 *
b0 )
b0 (
b0 $
1#
0"
b0 !
$end
#5000
1"
#10000
0"
0#
#15000
b1 0
b10 *
b110001 )
1"
#20000
0"
#25000
b0 -
b10 0
b11 /
b1 .
1"
#30000
0"
#35000
b0 0
b11 !
b11 $
b11 (
1"
#40000
0"
#45000
b1 0
b100 *
b10 )
1"
#50000
0"
#55000
bx -
b10 0
b0 /
b10 .
1"
#60000
0"
#65000
b110 -
b10 ,
b100 +
1"
#70000
0"
#75000
b0 0
b110 !
b110 $
b110 (
1"
#80000
0"
#85000
b1 0
b110 *
b101 )
1"
#90000
0"
#95000
b10 0
b101 .
1"
#100000
0"
#105000
1"
#110000
0"
#115000
b0 0
1"
#120000
0"
#125000
b1 0
b1000 *
b11 )
1"
#130000
0"
#135000
b10 -
b10 0
b11 .
1"
#140000
0"
#145000
1"
#150000
0"
#155000
b0 0
b10 !
b10 $
b10 (
1"
#160000
0"
#165000
b1 0
b1010 *
b100 )
1"
#170000
0"
#175000
b0 -
b10 0
b100 .
1"
#180000
0"
#185000
1"
#190000
0"
#195000
b0 0
b0 !
b0 $
b0 (
1"
#200000
0"
#205000
b1 0
b1100 *
b111 )
1"
#210000
0"
#215000
b1001 -
b10 0
b111 .
1"
#220000
0"
#225000
1"
#230000
0"
#235000
b0 0
b1001 !
b1001 $
b1001 (
1"
#240000
0"
#245000
b1 0
b1110 *
bx )
1"
#250000
0"
#255000
b0 -
b10 0
bx /
bx .
1"
#260000
0"
#265000
b0 0
1"
#270000
0"
#275000
b1 0
b0 *
1"
#280000
0"
#285000
b10 0
1"
#290000
0"
#295000
b0 0
1"
#300000
0"
#305000
b1 0
b10 *
b110001 )
1"
#310000
0"
#315000
b10 0
b11 /
b1 .
1"
#320000
0"
#325000
b0 0
b11 !
b11 $
b11 (
1"
#330000
0"
#335000
b1 0
b100 *
b10 )
1"
#340000
0"
#345000
b110 -
b10 0
b0 /
b10 .
1"
#350000
0"
#355000
1"
#360000
0"
#365000
b0 0
b110 !
b110 $
b110 (
1"
#370000
0"
#375000
b1 0
b110 *
b101 )
1"
#380000
0"
#385000
b10 0
b101 .
1"
#390000
0"
#395000
1"
#400000
0"
#405000
b0 0
1"
