cpu_new.v
module cpu (
    input wire clk,         // Clock signal
    input wire reset,       // Reset signal
    output wire [3:0] acc   // Output the value of accumulator register
);

    reg [3:0] PC;           // Program Counter
    reg [7:0] IR;           // Instruction Register (8-bit wide)
    reg [3:0] R0, R1;       // General purpose registers
    reg [3:0] ACC;          // Accumulator
    reg [3:0] memory [0:15];// Simple 4-bit memory for instructions
    reg [3:0] data_memory [0:15]; // Data memory
    reg [3:0] alu_out;      // Output of ALU
    reg [3:0] opcode, operand;
    reg [1:0] state;        // State variable for FSM
    reg [1:0] Data_PC;
    
    // States for instruction cycle
    parameter FETCH = 2'b00, DECODE = 2'b01, EXECUTE = 2'b10, LOAD = 2'b11;

    // ALU Logic
    always @(*) begin
        case(opcode)
            4'b0010: alu_out = R0 + R1;  // ADD
            4'b0011: alu_out = R0 - R1;  // SUB
            4'b0100: alu_out = R0 & R1;  // AND
            4'b0101: alu_out = R0 | R1;  // OR
            4'b0111: alu_out = ~(R0 ^ R1); //XNOR
            default: alu_out = 4'b0000;  // Default NOP
        endcase
    end

    // Control Unit FSM
    always @(posedge clk or posedge reset) begin
        if (reset) begin
            PC <= 4'b0000;
            Data_PC <= 2'b00;
            ACC <= 4'b0000;
            IR <= 8'b00000000;
            state <= FETCH;
        end else begin
            case (state)
                FETCH: begin
                    
                    IR <= {memory[PC + 1], memory[PC]};  // Fetch instruction
                    PC <= PC + 2;                        // Increment PC by 2
                    state <= DECODE;
                end
                DECODE: begin
                    opcode <= IR[3:0];      // Decode the opcode
                    operand <= IR[7:4];     // Decode the operand
                    state <= EXECUTE;
                end
                EXECUTE: begin
                    case (opcode)
                        4'b0000: state <= FETCH;  // NOP: go back to fetch
                        4'b0001: begin            // LOAD constant to ACC
                            ACC <= operand;
                            data_memory[Data_PC] <= operand;
                            Data_PC <= Data_PC + 1;      // Increment Data_PC for next load
                            if (Data_PC == 2'b10)        // Reset Data_PC if both R0 and R1 are loaded
                                Data_PC <= 2'b00;
                            state <= FETCH;
                        end
                        4'b0010, 4'b0011, 4'b0100, 4'b0101, 4'b0111: begin  // ALU operations
                            R0 <= data_memory[0];
                            R1 <= data_memory[1];  // Assume second register holds data for now
                            @(posedge clk) 
                            begin 
                                ACC <= alu_out;
                            end
                            @(posedge clk) begin
                                data_memory[Data_PC] <= ACC;
                                Data_PC <= Data_PC + 1;      // Increment Data_PC for next load
                                if (Data_PC == 2'b10)        // Reset Data_PC if both R0 and R1 are loaded
                                    Data_PC <= 2'b00;
                                state <= FETCH;
                            end

                        end
                        4'b0110: begin            // STORE ACC to memory
                            data_memory[operand] <= ACC;
                            state <= FETCH;
                        end
                        4'b0111: begin            // JMP to address
                            PC <= operand;
                            state <= FETCH;
                        end
                        default: state <= FETCH;  // Unknown opcode
                    endcase
                end
            endcase
        end
    end

    assign acc = ACC;  // Output the current value of ACC

endmodule

cpu_tb.v
module tb_cpu;

    // Testbench signals
    reg clk;
    reg reset;
    wire [3:0] acc;

    // Instantiate the CPU module
    cpu uut (
        .clk(clk),
        .reset(reset),
        .acc(acc)
    );

    // Clock generation
    always #5 clk = ~clk;

    // Test procedure
    initial begin
        // Initialize signals
        clk = 0;
        reset = 1;

        // Apply reset
        #10 reset = 0;

        // Test NOP (No operation)
        $display("Test NOP");
        uut.memory[0] = 4'b0000;  // NOP instruction
        #10;

        // Test LOAD instruction (loading a constant into ACC)
        $display("Test LOAD");
        uut.memory[1] = 4'b0001;  // LOAD opcode
        uut.memory[2] = 4'b0011;  // Operand: constant 3
        #10;
        if (acc != 4'b0011) $display("LOAD failed. Expected ACC = 3, got ACC = %b", acc);

        // Test ADD instruction (ACC = R0 + R1)
        $display("Test ADD");
        uut.memory[3] = 4'b0010;  // ADD opcode
        uut.memory[4] = 4'b0101;  // Operand: address 5, R1 = 5
        uut.memory[5] = 4'b0101;  // Operand: value 5
        #10;
        if (acc != 4'b0110) $display("ADD failed. Expected ACC = 6, got ACC = %b", acc);

        // Test SUB instruction (ACC = R0 - R1)
        $display("Test SUB");
        uut.memory[6] = 4'b0011;  // SUB opcode
        uut.memory[7] = 4'b0110;  // Operand: address 6, R1 = 6
        uut.memory[6] = 4'b0011;  // Operand: value 3
        #10;
        if (acc != 4'b0001) $display("SUB failed. Expected ACC = 1, got ACC = %b", acc);

        // Test AND instruction (ACC = R0 & R1)
        $display("Test AND");
        uut.memory[8] = 4'b0100;  // AND opcode
        uut.memory[9] = 4'b0111;  // Operand: address 7, R1 = 7
        uut.memory[9] = 4'b0011;  // Operand: value 3
        #10;
        if (acc != 4'b0011) $display("AND failed. Expected ACC = 3, got ACC = %b", acc);

        // Test OR instruction (ACC = R0 | R1)
        $display("Test OR");
        uut.memory[10] = 4'b0101;  // OR opcode
        uut.memory[11] = 4'b0010;  // Operand: address 8, R1 = 2
        uut.memory[11] = 4'b1100;  // Operand: value 12
        #10;
        if (acc != 4'b1110) $display("OR failed. Expected ACC = 14, got ACC = %b", acc);

        // Test STORE instruction (store ACC to memory)
        $display("Test STORE");
        uut.memory[12] = 4'b0110;  // STORE opcode
        uut.memory[13] = 4'b0001;  // Operand: memory address 1
        #10;
        if (uut.memory[1] != 4'b1110) $display("STORE failed. Expected memory[1] = 14, got memory[1] = %b", uut.memory[1]);
        $display("PC: %b", uut.PC);
        // Test JMP instruction (jump to address)
        $display("Test JMP");
        uut.PC = 4'b0000;
        $display("PC: %b", uut.PC);
        uut.memory[14] = 4'b0111;  // JMP opcode
        uut.memory[15] = 4'b0010;  // Operand: jump address 2
        #10;
        if (uut.PC != 4'b0010) $display("JMP failed. Expected PC = 2, got PC = %b", uut.PC);

        // End simulation
        $finish;
    end

endmodule

cpu_test.vcd
$date
	Tue Nov 12 23:51:09 2024
$end
$version
	Icarus Verilog
$end
$timescale
	1ps
$end
$scope module tb_cpu $end
$var wire 4 ! acc [3:0] $end
$var reg 1 " clk $end
$var reg 1 # reset $end
$scope module uut $end
$var wire 4 $ acc [3:0] $end
$var wire 1 " clk $end
$var wire 1 # reset $end
$var parameter 2 % DECODE $end
$var parameter 2 & EXECUTE $end
$var parameter 2 ' FETCH $end
$var parameter 2 ( LOAD $end
$var reg 4 ) ACC [3:0] $end
$var reg 2 * Data_PC [1:0] $end
$var reg 8 + IR [7:0] $end
$var reg 4 , PC [3:0] $end
$var reg 4 - R0 [3:0] $end
$var reg 4 . R1 [3:0] $end
$var reg 4 / alu_out [3:0] $end
$var reg 4 0 opcode [3:0] $end
$var reg 4 1 operand [3:0] $end
$var reg 2 2 state [1:0] $end
$upscope $end
$upscope $end
$enddefinitions $end
$comment Show the parameter values. $end
$dumpall
b11 (
b0 '
b10 &
b1 %
$end
#0
$dumpvars
b0 2
bx 1
bx 0
bx /
bx .
bx -
b0 ,
b0 +
b0 *
b0 )
b0 $
1#
0"
b0 !
$end
#5000
1"
#10000
0"
b1 *
0#
#15000
b1 2
b10 ,
b110001 +
1"
#20000
0"
#25000
b0 /
b10 2
b11 1
b1 0
1"
#30000
0"
#35000
b0 2
b10 *
b11 !
b11 $
b11 )
1"
#40000
0"
#45000
b1 2
b100 ,
b10 +
1"
#50000
0"
#55000
bx /
b10 2
b0 1
b10 0
1"
#60000
0"
#65000
b111 /
b11 .
b100 -
1"
#70000
0"
#75000
b111 !
b111 $
b111 )
1"
#80000
0"
#85000
b0 2
b0 *
1"
#90000
0"
#95000
b1 2
b110 ,
b101 +
1"
#100000
0"
#105000
b10 2
b101 0
1"
#110000
0"
#115000
1"
#120000
0"
#125000
1"
#130000
0"
#135000
b0 2
b1 *
1"
#140000
0"
#145000
b1 2
b1000 ,
b11 +
1"
#150000
0"
#155000
b1 /
b10 2
b11 0
1"
#160000
0"
#165000
b100 /
b111 -
1"
#170000
0"
#175000
b100 !
b100 $
b100 )
1"
#180000
0"
#185000
b0 2
b10 *
1"
#190000
0"
#195000
b1 2
b1010 ,
b100 +
1"
#200000
0"
#205000
b11 /
b10 2
b100 0
1"
#210000
0"
#215000
b100 /
b100 .
1"
#220000
0"
#225000
1"
#230000
0"
#235000
b0 2
b0 *
1"
#240000
0"
#245000
b1 2
b1100 ,
b111 +
1"
#250000
0"
#255000
b1100 /
b10 2
b111 0
1"
#260000
0"
#265000
1"
#270000
0"
#275000
b1100 !
b1100 $
b1100 )
1"
#280000
0"
#285000
b0 2
b1 *
1"
#290000
0"
#295000
b1 2
b1110 ,
bx +
1"
#300000
0"
#305000
b0 /
b10 2
bx 1
bx 0
1"
#310000
0"
#315000
b0 2
1"
#320000
0"
#325000
b1 2
b0 ,
1"
#330000
0"
#335000
b10 2
1"
#340000
0"
#345000
b0 2
1"
#350000
0"
#355000
b1 2
b10 ,
b110001 +
1"
#360000
0"
#365000
b10 2
b11 1
b1 0
1"
#370000
0"
#375000
b0 2
b10 *
b11 !
b11 $
b11 )
1"
#380000
0"
#385000
b1 2
b100 ,
b10 +
1"
#390000
0"
#395000
b1011 /
b10 2
b0 1
b10 0
1"
#400000
0"
#405000
b1111 /
b11 .
b1100 -
1"
